simple_auto_subtitle/__init__.py
simple_auto_subtitle/main.py
simple_auto_subtitle-0.1.0.dist-info/METADATA
simple_auto_subtitle-0.1.0.dist-info/WHEEL
simple_auto_subtitle-0.1.0.dist-info/entry_points.txt
simple_auto_subtitle-0.1.0.dist-info/licenses/LICENSE
simple_auto_subtitle-0.1.0.dist-info/RECORD
