Metadata-Version: 2.4
Name: simple-auto-subtitle
Version: 0.1.0
Summary: Automatic subtitle generation using Gemini AI
Project-URL: Homepage, https://github.com/yunfanye/auto_subtitle
Project-URL: Issues, https://github.com/yunfanye/auto_subtitle/issues
Project-URL: Repository, https://github.com/yunfanye/auto_subtitle
Author-email: yunfanye <yunfan.ye68@gmail.com>
License-Expression: MIT
License-File: LICENSE
Keywords: ai,captions,gemini,srt,subtitle,transcription,video
Classifier: Development Status :: 4 - Beta
Classifier: Intended Audience :: Developers
Classifier: Intended Audience :: Education
Classifier: Operating System :: OS Independent
Classifier: Programming Language :: Python :: 3
Classifier: Programming Language :: Python :: 3.8
Classifier: Programming Language :: Python :: 3.9
Classifier: Programming Language :: Python :: 3.10
Classifier: Programming Language :: Python :: 3.11
Classifier: Programming Language :: Python :: 3.12
Classifier: Topic :: Multimedia :: Video
Classifier: Topic :: Scientific/Engineering :: Artificial Intelligence
Classifier: Topic :: Text Processing :: Linguistic
Requires-Python: >=3.8
Requires-Dist: google-genai>=0.7.0
Requires-Dist: pydantic>=2.0.0
Requires-Dist: python-dotenv>=1.0.0
